pyasyncspeedtest/__init__.py
pyasyncspeedtest/runner/__init__.py
pyasyncspeedtest/runner/_internal.py
pyasyncspeedtest/runner/errors.py
pyasyncspeedtest/runner/models.py
pyasyncspeedtest/runner/speedtest.py
pyasyncspeedtest-0.1.0.dist-info/METADATA
pyasyncspeedtest-0.1.0.dist-info/WHEEL
pyasyncspeedtest-0.1.0.dist-info/top_level.txt
pyasyncspeedtest-0.1.0.dist-info/RECORD
