Metadata-Version: 2.4
Name: pyasyncspeedtest
Version: 0.1.0
Summary: Async-first Python speed test library for measuring network throughput
Author-email: Adel AbdElGawad <tech.adel87@gmail.com>
License-Expression: MIT
Project-URL: Homepage, https://github.com/adelabdelgawad/AsyncSpeedTest
Project-URL: Repository, https://github.com/adelabdelgawad/AsyncSpeedTest
Project-URL: Issues, https://github.com/adelabdelgawad/AsyncSpeedTest/issues
Keywords: speedtest,async,aiohttp,network,bandwidth,asyncio
Classifier: Development Status :: 4 - Beta
Classifier: Intended Audience :: Developers
Classifier: Topic :: System :: Networking
Classifier: Programming Language :: Python :: 3
Classifier: Programming Language :: Python :: 3.10
Classifier: Programming Language :: Python :: 3.11
Classifier: Programming Language :: Python :: 3.12
Classifier: Operating System :: OS Independent
Classifier: Framework :: AsyncIO
Requires-Python: >=3.10
Requires-Dist: aiohttp>=3.8.0
Provides-Extra: dev
Requires-Dist: pytest>=7.0.0; extra == "dev"
Requires-Dist: pytest-asyncio>=0.21.0; extra == "dev"
